{
  "match 1": { "winner": "dagger", "loser": "sword" },
  "match 2": { "winner": "staff", "loser": "bow" },
  "match 3": { "winner": "scythe", "loser": "staff" },
  "match 4": { "winner": "dagger", "loser": "staff" },
  "match 5": { "winner": "sword", "loser": "spear" },
  "match 6": { "winner": "sword", "loser": "shuriken" },
  "match 7": { "winner": "bow", "loser": "sword" },
  "match 8": { "winner": "shuriken", "loser": "spear" },
  "match 9": { "winner": "scythe", "loser": "dagger" },
  "match 10": { "winner": "shuriken", "loser": "dagger" },
  "match 11": { "winner": "bow", "loser": "scythe" },
  "match 12": { "winner": "sword", "loser": "shield" },
  "match 13": { "winner": "shuriken", "loser": "scythe" },
  "match 14": { "winner": "shield", "loser": "bow" },
  "match 15": { "winner": "shuriken", "loser": "bow" },
  "match 16": { "winner": "unarmed", "loser": "shuriken" },
  "match 17": { "winner": "scythe", "loser": "shield" },
  "match 18": { "winner": "shield", "loser": "unarmed" },
  "match 19": { "winner": "spear", "loser": "scythe" },
  "match 20": { "winner": "scythe", "loser": "bow" },
  "match 21": { "winner": "scythe", "loser": "bow" },
  "match 22": { "winner": "sword", "loser": "staff" },
  "match 23": { "winner": "sword", "loser": "staff" },
  "match 24": { "winner": "spear", "loser": "unarmed" },
  "match 25": { "winner": "unarmed", "loser": "spear" },
  "match 26": { "winner": "spear", "loser": "unarmed" },
  "match 27": { "winner": "dagger", "loser": "shield" },
  "match 28": { "winner": "shield", "loser": "dagger" },
  "match 29": { "winner": "dagger", "loser": "shield" },
  "match 30": { "winner": "sword", "loser": "scythe" },
  "match 31": { "winner": "scythe", "loser": "sword" },
  "match 32": { "winner": "sword", "loser": "scythe" },
  "match 33": { "winner": "spear", "loser": "dagger" },
  "match 34": { "winner": "dagger", "loser": "spear" },
  "match 35": { "winner": "spear", "loser": "dagger" },
  "match 36": { "winner": "sword", "loser": "spear" },
  "match 37": { "winner": "sword", "loser": "spear" },
  "match 38": { "winner": "sword", "loser": "wrench" },
  "match 39": { "winner": "shuriken", "loser": "wrench" },
  "match 40": { "winner": "wrench", "loser": "spear" },
  "match 41": { "winner": "hammer", "loser": "sword" },
  "match 42": { "winner": "unarmed", "loser": "wrench" },
  "match 43": { "winner": "wrench", "loser": "hammer" },
  "match 44": { "winner": "unarmed", "loser": "hammer" },
  "match 45": { "winner": "unarmed", "loser": "hammer" },
  "match 46": { "winner": "wrench", "loser": "bow" },
  "match 47": { "winner": "spear", "loser": "hammer" },
  "match 48": { "winner": "spear", "loser": "hammer" },
  "match 49": { "winner": "wrench", "loser": "staff" },
  "match 50": { "winner": "scythe", "loser": "wrench" },
  "match 51": { "winner": "hammer", "loser": "dagger" }
}
